{
  "appPageId" : "b45b6a8a-885d-430c-abfa-68a6cb461961",
  "componentName" : "siteforce:sldsTwoCol66Layout",
  "id" : "7613be27-8074-4141-805e-bcc2a47458fc",
  "label" : "Contact Us",
  "regions" : [ {
    "id" : "893673c1-dc63-4e3a-b533-59986248878d",
    "regionName" : "header",
    "type" : "region"
  }, {
    "components" : [ {
      "componentAttributes" : {
        "allowAttachments" : true,
        "attachmentLabel" : "Upload File",
        "buttonAlignment" : "center",
        "buttonBgColor" : "",
        "buttonBgHoverColor" : "",
        "buttonBorderColor" : "",
        "buttonMaxWidth" : "",
        "buttonRadius" : 0,
        "buttonTextColor" : "",
        "buttonTextHoverColor" : "",
        "callToAction" : false,
        "callToActionButtonText" : "",
        "callToActionText" : "",
        "callToActionUrl" : "",
        "confirmationSubtext" : "We’ll get back to you soon.",
        "confirmationText" : "Your case was created.",
        "guestQuickActionName" : "Select or configure a global action",
        "headerSubtitle" : "Tell us how we can help.",
        "headerTitle" : "Contact Customer Support",
        "quickActionName" : "NewCase",
        "requestSummaryText" : "Case summary"
      },
      "componentName" : "forceCommunity:contactSupportForm",
      "id" : "db2c5047-519b-43e2-a1f0-40cf01a32193",
      "renderPriority" : "NEUTRAL",
      "renditionMap" : { },
      "type" : "component"
    } ],
    "id" : "b71c1f04-f66c-4193-8841-78f4f8d902e4",
    "regionName" : "content",
    "type" : "region"
  }, {
    "components" : [ {
      "componentAttributes" : {
        "askConfirmationQuestion" : true,
        "confirmationMessageLabel" : "Got it!",
        "deflectionSubtitle" : "Find what you need here.",
        "deflectionTitle" : "Need Answers Fast?",
        "firstQuestion" : "Did this content solve your issue?",
        "maxResults" : 6,
        "measureDeflection" : true,
        "redirectUrl" : "",
        "secondQuestion" : "Stop creating your case?",
        "showArticles" : true,
        "showDiscussions" : false,
        "topicId" : ""
      },
      "componentName" : "forceCommunity:caseDeflection",
      "id" : "a61d3bfb-c838-4ac4-835c-2ba622064147",
      "renderPriority" : "NEUTRAL",
      "renditionMap" : { },
      "type" : "component"
    } ],
    "id" : "885fbaf7-1cff-44df-90a6-f52e709b9684",
    "regionName" : "sidebar",
    "type" : "region"
  }, {
    "id" : "44eeb0bf-b280-4c9e-835a-ccae9a452143",
    "regionName" : "footer",
    "type" : "region"
  }, {
    "components" : [ {
      "componentAttributes" : {
        "description" : "",
        "metaTags" : "",
        "title" : "Contact Us"
      },
      "componentName" : "forceCommunity:seoAssistant",
      "id" : "74f6f736-0554-4eb1-bd78-89edf8a4b4c8",
      "renditionMap" : { },
      "type" : "component"
    } ],
    "id" : "55f64b65-f15e-4eb4-b73d-61d385f2728d",
    "regionName" : "sfdcHiddenRegion",
    "type" : "region"
  } ],
  "themeLayoutType" : "Inner",
  "type" : "view",
  "viewType" : "contactsupport"
}